{"hash":"d6cdff1c4f3b0c6ffa0fb0ed0cc6a4b773d04a0e","data":{"strapi":{"videos":{"data":[{"attributes":{"title":"Fall Into Rise || Part 3 || NS || 19 April 2005","slug":"fall-into-rise-oror-part-3-oror-ns-oror-19-april-2005-ncydohyjb5y","description":"Title: Fall Into Rise Q&A Part 3 of 3\nName Program: Satsang\nSession on: Experience Freedom of Mind and End All Your Suffering\nDate: 19 April 2005\nVenue: Yellow Springs, Ohio, USA\n\nIn this video Supreme Pontiff of Hinduism HDH #Nithyananda Paramashivam answers questions of participants. He clarifies the concept of ‘Dropping’ and deepens the understanding about ‘Dropping In’.\n\nThe questions that HDH #Nithyananda Paramashivam answers are of incredible value to all of us, as we can all relate to the topics the participants inquire about.\n\nHow can we participate in our own #healing process?\nHow can we be free from physical, #emotional, and mental suffering by ‘Dropping’?\nHow does the world speeding up affect this process of ‘Dropping’, and how does it affect our #consciousness?\nWhat happens exactly in our inner world and what are the phases of ‘Dropping In’?\nWhat are the steps to ‘Drop’?\nWhen you ‘Fall into Rise’, can you still do the same thing every day?\n\nThese are only some of the topics that are covered in this video. Watch this video, just Drop and get the experience of ‘Falling In to Rise’ instantly!\n\n \n\n\n\n\n\n\nWebsite and Social Media: http://www.kailaasa.org","thumbnailURL":"https://i.ytimg.com/vi_webp/NcydoHYJb5Y/maxresdefault.webp","youtubeID":"NcydoHYJb5Y","viewCount":349,"eventDate":"2020-08-30","playlists":{"data":[{"id":"19"}]}}}]},"playlists":{"data":[{"attributes":{"title":"Popular Videos","description":"Popular and trending videos on KAILASA's Nithyananda TV","slug":"popular-videos","videos":{"data":[{"attributes":{"title":"3-Step Technique to Heal & Complete Your Relationships","slug":"3-step-technique-to-heal-and-complete-your-relationships-pets9notwou","thumbnailURL":"https://i.ytimg.com/vi_webp/PEtS9NoTwOU/maxresdefault.webp","viewCount":5249,"eventDate":"2018-09-26"}},{"attributes":{"title":"Shivoham Process - Purifying Sounds & Visualizations in the Mind & Body","slug":"shivoham-process-purifying-sounds-and-visualizations-in-the-mind-and-body-cff2vuroro4","thumbnailURL":"https://i.ytimg.com/vi_webp/Cff2VurORO4/maxresdefault.webp","viewCount":8185,"eventDate":"2018-09-26"}},{"attributes":{"title":"Let Wealth Be a Side-Effect of Your Spirituality","slug":"let-wealth-be-a-side-effect-of-your-spirituality-hsskrssjvcu","thumbnailURL":"https://i.ytimg.com/vi_webp/HSSkrSSJvCU/maxresdefault.webp","viewCount":3004,"eventDate":"2018-09-26"}},{"attributes":{"title":"Kailash - Spiritual Energy Center of the Universe, The Breathing Space of Shiva","slug":"kailash-spiritual-energy-center-of-the-universe-the-breathing-space-of-shiva-xwtqzvembn0","thumbnailURL":"https://i.ytimg.com/vi_webp/XwtQZVeMbn0/maxresdefault.webp","viewCount":5938,"eventDate":"2018-09-15"}},{"attributes":{"title":"Anything is Worthy of Giving Up To Be Established in The Supreme Self","slug":"anything-is-worthy-of-giving-up-to-be-established-in-the-supreme-self-zhecyrqqdbe","thumbnailURL":"https://i.ytimg.com/vi_webp/zHecyrQqDbE/maxresdefault.webp","viewCount":6439,"eventDate":"2018-09-14"}},{"attributes":{"title":"Anger is Neither Good Nor Bad, It is Pure Energy","slug":"anger-is-neither-good-nor-bad-it-is-pure-energy-jrhkzpkawwm","thumbnailURL":"https://i.ytimg.com/vi_webp/JrHKZpKAwWM/maxresdefault.webp","viewCount":7606,"eventDate":"2018-09-13"}},{"attributes":{"title":"Extraordinary Experiences of Yoga | Autobiography of The Avatar","slug":"extraordinary-experiences-of-yoga-or-autobiography-of-the-avatar-jh5zut5pyzk","thumbnailURL":"https://i.ytimg.com/vi_webp/jh5zUt5pyzk/maxresdefault.webp","viewCount":63766,"eventDate":"2018-09-13"}},{"attributes":{"title":"Haritaki - The Most Praised, Amazing Herb from Ayurveda","slug":"haritaki-the-most-praised-amazing-herb-from-ayurveda-dj2xulgnsps","thumbnailURL":"https://i.ytimg.com/vi_webp/dJ2XULGnSps/maxresdefault.webp","viewCount":15243,"eventDate":"2018-09-13"}},{"attributes":{"title":"Awakening Kundalini Shakti Using Trikona Mandala","slug":"awakening-kundalini-shakti-using-trikona-mandala-1voufcoivho","thumbnailURL":"https://i.ytimg.com/vi_webp/1VOufcOiVHo/maxresdefault.webp","viewCount":35546,"eventDate":"2018-09-09"}},{"attributes":{"title":"Kalabhairava & The 64 Forms of Shiva, Marvels of Temple Architecture","slug":"kalabhairava-and-the-64-forms-of-shiva-marvels-of-temple-architecture-6om7s2tsyjm","thumbnailURL":"https://i.ytimg.com/vi_webp/6OM7S2TSYjM/maxresdefault.webp","viewCount":7623,"eventDate":"2018-09-09"}}]}}}]}}},"context":{"slug":"fall-into-rise-oror-part-3-oror-ns-oror-19-april-2005-ncydohyjb5y"}}